lib/pyTSLPy/__init__.py
pyTSLPy/__init__.py
pyTSLPy-0.3.dist-info/METADATA
pyTSLPy-0.3.dist-info/WHEEL
pyTSLPy-0.3.dist-info/top_level.txt
pyTSLPy-0.3.dist-info/RECORD
